{
  "name": "DojoJS_Seppuku",
  "type": "dark",
  "colors": {
    "activityBar.activeBackground": "#040410",
    "activityBar.activeBorder": "#00FFFF",
    "activityBar.background": "#24242D",
    "activityBar.border": "#000000",
    "activityBar.dropBorder": "#00e0ff",
    "activityBar.foreground": "#00FFFF",
    "activityBar.inactiveForeground": "#040400",
    "activityBarBadge.background": "#00FFFF",
    "activityBarBadge.foreground": "#0F0000",
    "badge.background": "#00FFFF",
    "badge.foreground": "#0F0000",
    "bookmarks.overviewRuler": "#00000000",
    "breadcrumb.activeSelectionForeground": "#00e0ff",
    "breadcrumb.background": "#400008",
    "breadcrumb.focusForeground": "#00e0ff",
    "breadcrumb.foreground": "#8f8a74",
    "breadcrumbPicker.background": "#20212A",
    "button.background": "#07080b",
    "button.foreground": "#00e0ff",
    "button.hoverBackground": "#00f0ff48",
    "button.secondaryBackground": "#07080b",
    "button.secondaryForeground": "#ff1040",
    "button.secondaryHoverBackground": "#ff104044",
    "checkbox.background": "#020204",
    "checkbox.border": "#0cccff",
    "checkbox.foreground": "#00e0ff",
    "contrastActiveBorder": "#00000000",
    "contrastBorder": "#0F0000",
    "debugConsole.errorForeground": "#ff3333",
    "debugConsole.infoForeground": "#75beff",
    "debugConsole.sourceForeground": "#ffffff",
    "debugConsole.warningForeground": "#e6b450",
    "debugConsoleInputIcon.foreground": "#ff8080",
    "debugExceptionWidget.background": "#48040f",
    "debugExceptionWidget.border": "#cccccc",
    "debugIcon.breakpointForeground": "#00ffff",
    "debugToolBar.background": "#ee00ee",
    "debugToolBar.border": "#80ff00",
    "descriptionForeground": "#ee7480",
    "dropdown.background": "#07080b",
    "dropdown.border": "#0cccff",
    "dropdown.foreground": "#00e0ff",
    "dropdown.listBackground": "#12141a",
    "editor.background": "#0C0C12",
    "editor.findMatchBackground": "#000000",
    "editor.findMatchBorder": "#00ffa0",
    "editor.findMatchHighlightBackground": "#ff0a3844",
    "editor.findMatchHighlightBorder": "#ff0a38e0",
    "editor.findRangeHighlightBackground": "#000000",
    "editor.findRangeHighlightBorder": "#34bb14",
    "editor.focusedStackFrameHighlightBackground": "#e000e0",
    "editor.foldBackground": "#200206",
    "editor.foreground": "#ca6a6f",
    "editor.hoverHighlightBackground": "#020204",
    "editor.inactiveSelectionBackground": "#dddddd40",
    "editor.lineHighlightBackground": "#090a0d",
    "editor.lineHighlightBorder": "#090a0d",
    "editor.onTypeRenameBackground": "#e000e0",
    "editor.rangeHighlightBackground": "#00000080",
    "editor.rangeHighlightBorder": "#000000",
    "editor.selectionBackground": "#000000",
    "editor.selectionForeground": "#00e0ff",
    "editor.selectionHighlightBackground": "#000000",
    "editor.selectionHighlightBorder": "#0fffcc",
    "editor.snippetFinalTabstopHighlightBackground": "#ff2000",
    "editor.snippetFinalTabstopHighlightBorder": "#64000f",
    "editor.snippetTabstopHighlightBackground": "#300000a0",
    "editor.snippetTabstopHighlightBorder": "#00ffff",
    "editor.stackFrameHighlightBackground": "#00ff00",
    "editor.symbolHighlightBackground": "#ee00ee",
    "editor.symbolHighlightBorder": "#ee00ee",
    "editor.wordHighlightBackground": "#1f0000",
    "editor.wordHighlightBorder": "#aaaaaa",
    "editor.wordHighlightStrongBackground": "#020204",
    "editor.wordHighlightStrongBorder": "#cccccc",
    "editorBracketMatch.background": "#000000",
    "editorBracketMatch.border": "#0fffbb",
    "editorCodeLens.foreground": "#626a73",
    "editorCursor.background": "#400008",
    "editorCursor.foreground": "#00ffaa",
    "editorError.border": "#ff1f00",
    "editorError.foreground": "#ff1f00",
    "editorGroup.border": "#64000f",
    "editorGroup.dropBackground": "#00f0ff64",
    "editorGroup.emptyBackground": "#64000f",
    "editorGroup.focusedEmptyBorder": "#ff1f00",
    "editorGroupHeader.border": "#000002",
    "editorGroupHeader.noTabsBackground": "#0c0000",
    "editorGroupHeader.tabsBackground": "#20212A",
    "editorGroupHeader.tabsBorder": "#aeaeae",
    "editorGutter.addedBackground": "#0fffccdd",
    "editorGutter.background": "#111218",
    "editorGutter.commentRangeForeground": "#ee00ee",
    "editorGutter.deletedBackground": "#b01800",
    "editorGutter.foldingControlForeground": "#00ffff",
    "editorGutter.modifiedBackground": "#0cccffdd",
    "editorHint.border": "#ffee20",
    "editorHint.foreground": "#ffee20",
    "editorHoverWidget.background": "#280105",
    "editorHoverWidget.border": "#aaaaaa",
    "editorHoverWidget.foreground": "#d4d4d4",
    "editorHoverWidget.statusBarBackground": "#04040c",
    "editorIndentGuide.activeBackground": "#aaaaaa",
    "editorIndentGuide.background": "#ffffff0f",
    "editorInfo.border": "#ffee20",
    "editorInfo.foreground": "#ffee20",
    "editorLightBulb.foreground": "#ffee20",
    "editorLightBulbAutoFix.foreground": "#ffee20",
    "editorLineNumber.activeForeground": "#00e0ff",
    "editorLineNumber.foreground": "#72181e",
    "editorLink.activeForeground": "#00ff80",
    "editorMarkerNavigation.background": "#ee00ee",
    "editorMarkerNavigationError.background": "#ee00ee",
    "editorMarkerNavigationInfo.background": "#ee00ee",
    "editorMarkerNavigationWarning.background": "#ee00ee",
    "editorOverviewRuler.addedForeground": "#0fffcc",
    "editorOverviewRuler.background": "#07080b",
    "editorOverviewRuler.border": "#64000f",
    "editorOverviewRuler.bracketMatchForeground": "#ff0a32",
    "editorOverviewRuler.commonContentForeground": "#bbbbbbe0",
    "editorOverviewRuler.currentContentForeground": "#20b0ffe0",
    "editorOverviewRuler.deletedForeground": "#aa1a00",
    "editorOverviewRuler.errorForeground": "#ff1f00",
    "editorOverviewRuler.findMatchForeground": "#cccccc",
    "editorOverviewRuler.incomingContentForeground": "#20ffb0e0",
    "editorOverviewRuler.infoForeground": "#ffee20",
    "editorOverviewRuler.modifiedForeground": "#0cccff",
    "editorOverviewRuler.rangeHighlightForeground": "#901018",
    "editorOverviewRuler.selectionHighlightForeground": "#00e0ff",
    "editorOverviewRuler.warningForeground": "#e8ff00",
    "editorOverviewRuler.wordHighlightForeground": "#00a0ff",
    "editorOverviewRuler.wordHighlightStrongForeground": "#00ffa0",
    "editorPane.background": "#111218",
    "editorRuler.foreground": "#a000182f",
    "editorSuggestWidget.background": "#2d0205",
    "editorSuggestWidget.border": "#cccccc",
    "editorSuggestWidget.foreground": "#eeeeee",
    "editorSuggestWidget.highlightForeground": "#00ffee",
    "editorSuggestWidget.selectedBackground": "#02020499",
    "editorUnnecessaryCode.border": "#000000",
    "editorUnnecessaryCode.opacity": "#00000099",
    "editorWarning.border": "#e8ff00",
    "editorWarning.foreground": "#e8ff00",
    "editorWhitespace.foreground": "#c0000a",
    "editorWidget.background": "#101014",
    "editorWidget.border": "#8a2a34",
    "editorWidget.foreground": "#cccccc",
    "editorWidget.resizeBorder": "#180000",
    "errorForeground": "#ff1f00",
    "extensionBadge.remoteBackground": "#e000e0",
    "extensionBadge.remoteForeground": "#e000e0",
    "extensionButton.prominentBackground": "#000000",
    "extensionButton.prominentForeground": "#ffffff",
    "extensionButton.prominentHoverBackground": "#008090",
    "focusBorder": "#00000000",
    "foreground": "#bbbbbb",
    "gitDecoration.addedResourceForeground": "#0fffcc",
    "gitDecoration.conflictingResourceForeground": "#ff1f00",
    "gitDecoration.deletedResourceForeground": "#b01800",
    "gitDecoration.ignoredResourceForeground": "#80444c",
    "gitDecoration.modifiedResourceForeground": "#0cccff",
    "gitDecoration.stageDeletedResourceForeground": "#b0180088",
    "gitDecoration.stageModifiedResourceForeground": "#0cccff88",
    "gitDecoration.submoduleResourceForeground": "#c480aa",
    "gitDecoration.untrackedResourceForeground": "#566472",
    "icon.foreground": "#ffffff",
    "imagePreview.border": "#ee00ee",
    "input.background": "#05050a",
    "input.border": "#303030",
    "input.foreground": "#c0353d",
    "input.placeholderForeground": "#414856",
    "inputOption.activeBackground": "#3c425066",
    "inputOption.activeBorder": "#e6b450",
    "inputOption.activeForeground": "#cccccc",
    "inputValidation.errorBackground": "#07080b",
    "inputValidation.errorBorder": "#ff3333",
    "inputValidation.errorForeground": "#ff0000",
    "inputValidation.infoBackground": "#fff08048",
    "inputValidation.infoBorder": "#ffe024",
    "inputValidation.infoForeground": "#ffe024",
    "inputValidation.warningBackground": "#d0ff0034",
    "inputValidation.warningBorder": "#f0ff00",
    "inputValidation.warningForeground": "#f0ff00",
    "list.activeSelectionBackground": "#b0101a48",
    "list.activeSelectionForeground": "#1a1010",
    "list.deemphasizedForeground": "#88888888",
    "list.dropBackground": "#00e0ff",
    "list.errorForeground": "#ff1f00",
    "list.filterMatchBackground": "#20202080",
    "list.filterMatchBorder": "#20202080",
    "list.focusBackground": "#18eec020",
    "list.focusForeground": "#20ffcc",
    "list.highlightForeground": "#00e0ff",
    "list.hoverBackground": "#00f0ff28",
    "list.hoverForeground": "#00e0ff",
    "list.inactiveFocusBackground": "#111218",
    "list.inactiveSelectionBackground": "#cccccc50",
    "list.inactiveSelectionForeground": "#cccccc",
    "list.invalidItemForeground": "#ff1f00",
    "list.warningForeground": "#e8ff00",
    "listFilterWidget.background": "#20202040",
    "listFilterWidget.noMatchesOutline": "#ff1f00",
    "listFilterWidget.outline": "#0cccff",
    "menu.background": "#1e0004",
    "menu.border": "#aaaaaa",
    "menu.foreground": "#b8b8b8",
    "menu.selectionBackground": "#cccccc1c",
    "menu.selectionBorder": "#000000",
    "menu.selectionForeground": "#00e0c0",
    "menu.separatorBackground": "#64000f",
    "menubar.selectionBackground": "#00000000",
    "menubar.selectionBorder": "#00000000",
    "menubar.selectionForeground": "#00e0ff",
    "merge.border": "#20ffb0a0",
    "merge.commonContentBackground": "#dddddd28",
    "merge.commonHeaderBackground": "#dddddd48",
    "merge.currentContentBackground": "#20b0ff50",
    "merge.currentHeaderBackground": "#20b0ff80",
    "merge.incomingContentBackground": "#20ffb040",
    "merge.incomingHeaderBackground": "#20ffb060",
    "minimap.background": "#060608",
    "minimap.errorHighlight": "#ff1f00",
    "minimap.findMatchHighlight": "#00a0ff",
    "minimap.selectionHighlight": "#00ffdd",
    "minimap.warningHighlight": "#e8ff00",
    "minimapGutter.addedBackground": "#0fffcc",
    "minimapGutter.deletedBackground": "#aa1a00",
    "minimapGutter.modifiedBackground": "#0cccff",
    "minimapSlider.activeBackground": "#00f0ff20",
    "minimapSlider.background": "#e0e0e040",
    "minimapSlider.hoverBackground": "#00f0ff80",
    "notificationCenterHeader.background": "#07080b",
    "notificationLink.foreground": "#00ffaa",
    "notifications.background": "#ffee1460",
    "notifications.border": "#ffee20",
    "notifications.foreground": "#ffee20",
    "notificationsErrorIcon.foreground": "#ff1f00",
    "notificationsInfoIcon.foreground": "#ffee20",
    "notificationsWarningIcon.foreground": "#e8ff00",
    "panel.background": "#040408",
    "panel.border": "#901018",
    "panel.dropBorder": "#00e0ff",
    "panelInput.border": "#0cccff",
    "panelSection.border": "#901018",
    "panelSection.dropBackground": "#00f0ff64",
    "panelSectionHeader.background": "#07080b",
    "panelSectionHeader.border": "#cccccc",
    "panelSectionHeader.foreground": "#cccccc",
    "panelTitle.activeBorder": "#00ddff",
    "panelTitle.activeForeground": "#0ab8f8",
    "panelTitle.inactiveForeground": "#aeaeae",
    "peekView.border": "#ff2428",
    "peekViewEditor.background": "#07080b",
    "peekViewEditor.matchHighlightBackground": "#0c0000",
    "peekViewEditor.matchHighlightBorder": "#cccccc",
    "peekViewEditorGutter.background": "#07080b",
    "peekViewResult.background": "#07080b",
    "peekViewResult.fileForeground": "#202020",
    "peekViewResult.lineForeground": "#101010",
    "peekViewResult.matchHighlightBackground": "#20212A",
    "peekViewResult.selectionBackground": "#00f0ff3c",
    "peekViewResult.selectionForeground": "#ffffff",
    "peekViewTitle.background": "#07080b",
    "peekViewTitleDescription.foreground": "#cccccc",
    "peekViewTitleLabel.foreground": "#cccccc",
    "pickerGroup.border": "#cccccc",
    "pickerGroup.foreground": "#cccccc",
    "problemsErrorIcon.foreground": "#ff1f00",
    "problemsInfoIcon.foreground": "#ff1f00",
    "problemsWarningIcon.foreground": "#ff1f00",
    "progressBar.background": "#07080b",
    "quickInput.background": "#20060d",
    "quickInput.foreground": "#aaaaaa",
    "quickInputTitle.background": "#ee00ee",
    "scm.providerBorder": "#ee00ee",
    "scrollbar.shadow": "#000000",
    "scrollbarSlider.activeBackground": "#00b0bf",
    "scrollbarSlider.background": "#002070",
    "scrollbarSlider.hoverBackground": "#00e0ff",
    "searchEditor.findMatchBackground": "#000000",
    "searchEditor.findMatchBorder": "#00e0ff",
    "searchEditor.textInputBorder": "#00e0ff",
    "selection.background": "#ff30484f",
    "settings.checkboxBackground": "#000000",
    "settings.checkboxBorder": "#000000",
    "settings.checkboxForeground": "#dd2840",
    "settings.dropdownBackground": "#101010",
    "settings.dropdownBorder": "#a0a0a0",
    "settings.dropdownForeground": "#bbbbbb",
    "settings.dropdownListBorder": "#a0a0a0",
    "settings.focusedRowBackground": "#30050e",
    "settings.headerForeground": "#b82f3a",
    "settings.modifiedItemIndicator": "#dd2840",
    "settings.numberInputBackground": "#080808",
    "settings.numberInputBorder": "#aaaaaa",
    "settings.numberInputForeground": "#dd2840",
    "settings.textInputBackground": "#000000",
    "settings.textInputBorder": "#aaaaaa",
    "settings.textInputForeground": "#bbbbbb",
    "sideBar.background": "#1A1A1A",
    "sideBar.border": "#64000f",
    "sideBar.dropBackground": "#00f0ff64",
    "sideBar.foreground": "#aaaaaa",
    "sideBarSectionHeader.background": "#1E202A",
    "sideBarSectionHeader.border": "#aaaaaa",
    "sideBarSectionHeader.foreground": "#AAAAAA",
    "sideBarTitle.foreground": "#cccccc",
    "statusBar.background": "#00143C",
    "statusBar.border": "#B4B4B4",
    "statusBar.debuggingBackground": "#07080b",
    "statusBar.debuggingForeground": "#aaaaaa",
    "statusBar.foreground": "#48EEFF",
    "statusBar.noFolderBackground": "#07080b",
    "statusBarItem.activeBackground": "#901018",
    "statusBarItem.hoverBackground": "#90101880",
    "statusBarItem.prominentBackground": "#07080b",
    "statusBarItem.prominentForeground": "#901018",
    "statusBarItem.prominentHoverBackground": "#00000030",
    "symbolIcon.typeParameterForeground": "#0cca85",
    "tab.activeBackground": "#20212A",
    "tab.activeBorder": "#aeaeae",
    "tab.activeBorderTop": "#20212A",
    "tab.activeForeground": "#00FFFF",
    "tab.activeModifiedBorder": "#90101800",
    "tab.border": "#20212A",
    "tab.hoverBackground": "#20212A",
    "tab.hoverBorder": "#00FFAA",
    "tab.hoverForeground": "#00FFAA",
    "tab.inactiveBackground": "#20212A",
    "tab.inactiveForeground": "#a0a0a0",
    "tab.inactiveModifiedBorder": "#90101800",
    "tab.lastPinnedBorder": "#20212A",
    "tab.unfocusedActiveBackground": "#20212A",
    "tab.unfocusedActiveBorder": "#aeaeae",
    "tab.unfocusedActiveBorderTop": "#20212A",
    "tab.unfocusedActiveForeground": "#00FFFF",
    "tab.unfocusedActiveModifiedBorder": "#90101800",
    "tab.unfocusedHoverBackground": "#20212A",
    "tab.unfocusedHoverBorder": "#20212A",
    "tab.unfocusedHoverForeground": "#00FFAA",
    "tab.unfocusedInactiveBackground": "#20212A",
    "tab.unfocusedInactiveForeground": "#99999999",
    "tab.unfocusedInactiveModifiedBorder": "#00000000",
    "terminal.ansiBlack": "#000000",
    "terminal.ansiBlue": "#22aaeec4",
    "terminal.ansiBrightBlack": "#484a56",
    "terminal.ansiBrightBlue": "#22aaee",
    "terminal.ansiBrightCyan": "#00f0ffcc",
    "terminal.ansiBrightGreen": "#0ccca5cc",
    "terminal.ansiBrightMagenta": "#ffee99cc",
    "terminal.ansiBrightRed": "#f07178cc",
    "terminal.ansiBrightWhite": "#eeeeeecc",
    "terminal.ansiBrightYellow": "#ffb454cc",
    "terminal.ansiCyan": "#0ccccfcc",
    "terminal.ansiGreen": "#0bb333cc",
    "terminal.ansiMagenta": "#dd3dddcc",
    "terminal.ansiRed": "#f11122cc",
    "terminal.ansiWhite": "#cccccccc",
    "terminal.ansiYellow": "#daaa1acc",
    "terminal.background": "#121215",
    "terminal.border": "#aa1810",
    "terminal.foreground": "#ff5056",
    "terminal.selectionBackground": "#64000f64",
    "terminalCursor.background": "#00ffc4",
    "terminalCursor.foreground": "#ff0000",
    "textBlockQuote.background": "#0c0000",
    "textBlockQuote.border": "#e000e0",
    "textCodeBlock.background": "#07080b",
    "textLink.activeForeground": "#e6b450",
    "textLink.foreground": "#e6b450",
    "textPreformat.foreground": "#0cca85",
    "textSeparator.foreground": "#aa1018",
    "titleBar.activeBackground": "#06060F",
    "titleBar.activeForeground": "#CCCCA0",
    "titleBar.border": "#50ff00",
    "titleBar.inactiveBackground": "#383830",
    "titleBar.inactiveForeground": "#808074",
    "tree.indentGuidesStroke": "#ff3020aa",
    "walkThrough.embeddedEditorBackground": "#e000e0",
    "welcomePage.background": "#12141a",
    "welcomePage.buttonBackground": "#07080b",
    "welcomePage.buttonHoverBackground": "#00f0ff48",
    "widget.shadow": "#000000",
    "window.activeBorder": "#ff0434",
    "window.inactiveBorder": "#40000a"

    //"bookmarks.lineBackground": "#00000000",
    //"bookmarks.lineBorder": "#00000000",
    //"charts.blue": "#ffee20",
    //"charts.foreground": "#bbbbbb",
    //"charts.green": "#89d185",
    //"charts.lines": "#bbbbbb80",
    //"charts.orange": "#00a0ff",
    //"charts.purple": "#b180d7",
    //"charts.red": "#ff1f00",
    //"charts.yellow": "#e8ff00",
    //"debugIcon.breakpointCurrentStackframeForeground": "#ffcc00",
    //"debugIcon.breakpointDisabledForeground": "#848484",
    //"debugIcon.breakpointStackframeForeground": "#89d185",
    //"debugIcon.breakpointUnverifiedForeground": "#848484",
    //"debugIcon.continueForeground": "#75beff",
    //"debugIcon.disconnectForeground": "#f48771",
    //"debugIcon.pauseForeground": "#75beff",
    //"debugIcon.restartForeground": "#89d185",
    //"debugIcon.startForeground": "#89d185",
    //"debugIcon.stepBackForeground": "#75beff",
    //"debugIcon.stepIntoForeground": "#75beff",
    //"debugIcon.stepOutForeground": "#75beff",
    //"debugIcon.stepOverForeground": "#75beff",
    //"debugIcon.stopForeground": "#f48771",
    //"debugTokenExpression.boolean": "#4e94ce",
    //"debugTokenExpression.error": "#f48771",
    //"debugTokenExpression.name": "#c586c0",
    //"debugTokenExpression.number": "#b5cea8",
    //"debugTokenExpression.string": "#ce9178",
    //"debugTokenExpression.value": "#cccccc99",
    //"debugView.exceptionLabelBackground": "#6c2022",
    //"debugView.exceptionLabelForeground": "#bbbbbb",
    //"debugView.stateLabelBackground": "#88888844",
    //"debugView.stateLabelForeground": "#bbbbbb",
    //"debugView.valueChangedHighlight": "#569cd6",
    //"diffEditor.diagonalFill": "#cccccc33",
    //"diffEditor.insertedTextBackground": "#9bb95533",
    //"diffEditor.removedTextBackground": "#ff000033",
    //"editorActiveLineNumber.foreground": "#c6c6c6",
    //"gitlens.gutterBackgroundColor": "#ffffff13",
    //"gitlens.gutterForegroundColor": "#bebebe",
    //"gitlens.gutterUncommittedForegroundColor": "#00bcf299",
    //"gitlens.lineHighlightBackgroundColor": "#00bcf233",
    //"gitlens.lineHighlightOverviewRulerColor": "#00bcf299",
    //"gitlens.trailingLineBackgroundColor": "#00000000",
    //"gitlens.trailingLineForegroundColor": "#99999959",
    //"gitlens.viewChangesToPullIconColor": "#b15e35",
    //"gitlens.viewChangesToPushIconColor": "#35b15e",
    //"gitlens.viewCommitToPushIconColor": "#35b15e",
    //"notebook.cellBorderColor": "#90101866",
    //"notebook.cellHoverBackground": "#90101833",
    //"notebook.cellInsertionIndicator": "#00000000",
    //"notebook.cellStatusBarItemHoverBackground": "#ffffff26",
    //"notebook.cellToolbarSeparator": "#80808059",
    //"notebook.focusedCellBackground": "#90101866",
    //"notebook.focusedCellBorder": "#ffffff1f",
    //"notebook.focusedEditorBorder": "#00000000",
    //"notebook.focusedRowBorder": "#ffffff1f",
    //"notebook.outputContainerBackgroundColor": "#90101866",
    //"notebook.rowHoverBackground": "#30050e80",
    //"notebook.symbolHighlightBackground": "#ffffff0b",
    //"notebookScrollbarSlider.activeBackground": "#00b0bf",
    //"notebookScrollbarSlider.background": "#a01820",
    //"notebookScrollbarSlider.hoverBackground": "#00e0ff",
    //"notebookStatusErrorIcon.foreground": "#ff1f00",
    //"notebookStatusRunningIcon.foreground": "#bbbbbb",
    //"notebookStatusSuccessIcon.foreground": "#89d185",
    //"statusBar.debuggingBorder": "#020204",
    //"statusBar.noFolderBorder": "#020204",
    //"statusBar.noFolderForeground": "#dddddd",
    //"statusBarItem.remoteBackground": "#020204",
    //"statusBarItem.remoteForeground": "#00ffff",
    //"symbolIcon.arrayForeground": "#bbbbbb",
    //"symbolIcon.booleanForeground": "#bbbbbb",
    //"symbolIcon.classForeground": "#ee9d28",
    //"symbolIcon.colorForeground": "#bbbbbb",
    //"symbolIcon.constantForeground": "#bbbbbb",
    //"symbolIcon.constructorForeground": "#b180d7",
    //"symbolIcon.enumeratorForeground": "#ee9d28",
    //"symbolIcon.enumeratorMemberForeground": "#75beff",
    //"symbolIcon.eventForeground": "#ee9d28",
    //"symbolIcon.fieldForeground": "#75beff",
    //"symbolIcon.fileForeground": "#bbbbbb",
    //"symbolIcon.folderForeground": "#bbbbbb",
    //"symbolIcon.functionForeground": "#b180d7",
    //"symbolIcon.interfaceForeground": "#75beff",
    //"symbolIcon.keyForeground": "#bbbbbb",
    //"symbolIcon.keywordForeground": "#bbbbbb",
    //"symbolIcon.methodForeground": "#b180d7",
    //"symbolIcon.moduleForeground": "#bbbbbb",
    //"symbolIcon.namespaceForeground": "#bbbbbb",
    //"symbolIcon.nullForeground": "#bbbbbb",
    //"symbolIcon.numberForeground": "#bbbbbb",
    //"symbolIcon.objectForeground": "#bbbbbb",
    //"symbolIcon.operatorForeground": "#bbbbbb",
    //"symbolIcon.packageForeground": "#bbbbbb",
    //"symbolIcon.propertyForeground": "#bbbbbb",
    //"symbolIcon.referenceForeground": "#bbbbbb",
    //"symbolIcon.snippetForeground": "#bbbbbb",
    //"symbolIcon.stringForeground": "#bbbbbb",
    //"symbolIcon.structForeground": "#bbbbbb",
    //"symbolIcon.textForeground": "#bbbbbb",
    //"symbolIcon.unitForeground": "#bbbbbb",
    //"symbolIcon.variableForeground": "#75beff"
  },

  "tokenColors": [
    /*
    ______________________________________
    ->> Supported Languages
        --> JavaScript 
        --> JSON/JSONc
        --> HTML
        --> CSS
    ______________________________________                                         */

    // Non Language Specific Tokens
    {
      "name": "Info Text Style",
      "scope": "token.info-token",
      "settings": {
        "foreground": "#EEE333",
        "fontStyle": "bold"
      }
    },

    {
      "name": "Warning Text Style",
      "scope": "token.warn-token",
      "settings": {
        "foreground": "#DFFF04"
      }
    },

    {
      "name": "Error Text Style",
      "scope": "token.error-token",
      "settings": {
        "foreground": "#FF2004"
      }
    },

    {
      "name": "Debugging Text Style",
      "scope": "token.debug-token",
      "settings": {
        "foreground": "#40CC04"
      }
    },

    {
      "name": "Fundamental Tokens",
      "scope": [
        "source.js",
        "source.json",
        "source.json.comments",
        "source.css",
        "text.html"
      ],
      "settings": {
        "foreground": "#AAAAAA",
        "fontStyle": ""
      }
    },

    {
      "name": "BLOCK-COMMENTS",
      "scope": "comment.block",
      "settings": {
        "foreground": "#4C5678",
        "fontStyle": "italic"
      }
    },
    {
      "name": "BLOCK-COMMENTS",
      "scope": "comment.line.double-slash",
      "settings": {
        "foreground": "#6C484A",
        "fontStyle": "italic"
      }
    },

    {
      "name": "STRINGS",
      "scope": ["string.quoted.single", "string.quoted.double"],
      "settings": {
        "foreground": "#9F7A5A",
        "fontStyle": "italic"
      }
    },

    {
      "name": "STRINGS => JSON/JS_OBJECT PROPERTIES",
      "scope": ["support.type.property-name.json", "string.unquoted.js"],
      "settings": {
        "foreground": "#b84056",
        "fontStyle": ""
      }
    },

    {
      "name": "PUNCTUATION",
      "scope": "punctuation",
      "settings": {
        "foreground": "#00FF00",
        "fontStyle": "bold"
      }
    },

    {
      "name": "PUNCTUATION ==> BRIGHT-N-BOLD",
      "scope": [
        "punctuation.terminator",
        "punctuation.accessor",
        "punctuation.separator"
      ],
      "settings": {
        "foreground": "#FF7038",
        "fontStyle": ""
      }
    },
    {
      "name": "PUNCTUATION",
      "scope": [
        "meta.brace",
        "punctuation.definition",
        "punctuation.separator.dictionary.key-value",
        "punctuation.support.type.property-name"
      ],
      "settings": {
        "foreground": "#FF7038",
        "fontStyle": ""
      }
    },

    {
      "name": "PUNCUATION ==> STRING TEMPLATE LITERALS",
      "scope": "punctuation.definition.template-expression",
      "settings": {
        "foreground": "#B27078",
        "fontStyle": ""
      }
    },

    {
      "name": "PUNCUATION ==> COMMENTS",
      "scope": "punctuation.definition.comment",
      "settings": {
        "foreground": "#6C484A",
        "fontStyle": ""
      }
    },

    {
      "name": "STORAGE-TYPES",
      "scope": "storage",
      "settings": {
        "foreground": "#FF5460",
        "fontStyle": ""
      }
    },
    {
      "name": "CONTROL",
      "scope": "keyword",
      "settings": {
        "foreground": "#90FF00",
        "fontStyle": ""
      }
    },

    {
      "name": "CONTROL",
      "scope": "keyword.control",
      "settings": {
        "foreground": "#FF6000",
        "fontStyle": ""
      }
    },
    {
      "name": "OPERATORS",
      "scope": "keyword.operator",
      "settings": {
        "foreground": "#EF4040",
        "fontStyle": ""
      }
    },
    {
      "name": "OPERATORS",
      "scope": "keyword.operator.expression",
      "settings": {
        "foreground": "#FF6000",
        "fontStyle": ""
      }
    },

    {
      "name": "OPERATERS => ARITHMATIC",
      "scope": "keyword.operator.arithmetic",
      "settings": {
        "foreground": "#EF4040",
        "fontStyle": "bold"
      }
    },

    {
      "name": "CONSTANTS",
      "scope": "constant",
      "settings": {
        "foreground": "",
        "fontStyle": ""
      }
    },
    {
      "name": "CONSTANTS => NUMERIC",
      "scope": ["constant.numeric"],
      "settings": {
        "foreground": "",
        "fontStyle": ""
      }
    },
    {
      "name": "CONSTANTS => CHARACTERS, ESCAPED_CHARACTERS",
      "scope": "constant.character.escape",
      "settings": {
        "foreground": "",
        "fontStyle": ""
      }
    },

    // {
    //   "name": "VARIABLES",
    //   "scope": "variable",
    //   "settings": {
    //     "foreground": "",
    //     "fontStyle": ""
    //   }
    // },
    {
      "name": "VARIABLES => PARAMETERS, THIS",
      "scope": [
        "variable.parameter",
        "variable.language.this"
        // "meta.parameters",
        // "meta.function.parameters"
      ],
      "settings": {
        "foreground": "#44AACC",
        "fontStyle": "italic"
      }
    },
    {
      "name": "METHODS",
      "scope": "meta.definition.method",
      "settings": {
        "foreground": "#44AACC",
        "fontStyle": ""
      }
    },

    {
      "name": "OBJECTS",
      "scope": [
        "variable.other.object",
        "entity.name.type",
        "support.class.node",
        "support.class"
      ],
      "settings": {
        "foreground": "#44AACC",
        "fontStyle": ""
      }
    }
  ]
}
